llm_bedrock_titan_image.py
llm_bedrock_titan_image-1.0.5.dist-info/LICENSE
llm_bedrock_titan_image-1.0.5.dist-info/METADATA
llm_bedrock_titan_image-1.0.5.dist-info/WHEEL
llm_bedrock_titan_image-1.0.5.dist-info/entry_points.txt
llm_bedrock_titan_image-1.0.5.dist-info/top_level.txt
llm_bedrock_titan_image-1.0.5.dist-info/RECORD
