Metadata-Version: 2.1
Name: llm-bedrock-titan-image
Version: 1.0.5
Summary: An LLM plugin for supporting Amazon Titan image generators on Amazon Bedrock.
Author: Constantin Gonzalez
License: Apache-2.0
Project-URL: Homepage, https://github.com/zalez/llm-bedrock-titan-image
Project-URL: Changelog, https://github.com/zalez/llm-bedrock-titan-image/releases
Project-URL: Issues, https://github.com/zalez/llm-bedrock-titan-image/issues
Classifier: License :: OSI Approved :: Apache Software License
Requires-Python: >=3.8
License-File: LICENSE
Requires-Dist: llm >=0.15
Requires-Dist: pydantic >=2.8.0
Requires-Dist: boto3 >=1.35.0
Requires-Dist: webcolors >=24.8.0
Requires-Dist: Pillow >=10.4.0
Requires-Dist: requests >=2.32.3
Requires-Dist: build >=1.2.2.post1
